blogger_to_hugo.py
blogger_to_hugo-1.0.1.dist-info/LICENSE.txt
blogger_to_hugo-1.0.1.dist-info/METADATA
blogger_to_hugo-1.0.1.dist-info/WHEEL
blogger_to_hugo-1.0.1.dist-info/entry_points.txt
blogger_to_hugo-1.0.1.dist-info/top_level.txt
blogger_to_hugo-1.0.1.dist-info/RECORD
