Metadata-Version: 2.1
Name: blogger-to-hugo
Version: 1.0.1
Summary: Command line tool to convert Blogger posts to Hugo
Home-page: https://bitbucket.org/petraszd/blogger-to-hugo
Author: Petras Zdanavicius
Author-email: petraszd@gmail.com
License: UNKNOWN
Keywords: blogger hugo command line utility
Platform: UNKNOWN
Classifier: Environment :: Console
Classifier: License :: OSI Approved :: MIT License
Classifier: Topic :: Utilities
Classifier: Programming Language :: Python :: 2
Classifier: Programming Language :: Python :: 2.7
Classifier: Programming Language :: Python :: 3
Classifier: Programming Language :: Python :: 3.5
Classifier: Programming Language :: Python :: 3.6
Requires-Dist: awesome-slugify
Requires-Dist: beautifulsoup4
Requires-Dist: Pillow
Requires-Dist: pypandoc
Requires-Dist: python-dateutil
Requires-Dist: requests
Requires-Dist: toml
Provides-Extra: dev
Provides-Extra: test
